pjdev_op/__about__.py
pjdev_op/__init__.py
pjdev_op/models.py
pjdev_op/op_service.py
pjdev_op-4.6.3.dist-info/METADATA
pjdev_op-4.6.3.dist-info/WHEEL
pjdev_op-4.6.3.dist-info/licenses/LICENSE.txt
pjdev_op-4.6.3.dist-info/RECORD
